dartmouthbanner/Banner.py
dartmouthbanner/__init__.py
python_dartmouthbanner-1.0.dist-info/DESCRIPTION.rst
python_dartmouthbanner-1.0.dist-info/METADATA
python_dartmouthbanner-1.0.dist-info/metadata.json
python_dartmouthbanner-1.0.dist-info/RECORD
python_dartmouthbanner-1.0.dist-info/top_level.txt
python_dartmouthbanner-1.0.dist-info/WHEEL
