Metadata-Version: 2.0
Name: python-dartmouthbanner
Version: 1.0
Summary: Python API for interacting with Dartmouth Banner
Home-page: https://github.com/dado3212/python-dartmouthbanner
Author: Alex Beals
Author-email: Alex.Beals.18@dartmouth.edu
License: BSD
Keywords: api dartmouth banner
Platform: UNKNOWN
Classifier: Development Status :: 3 - Alpha
Classifier: Intended Audience :: Developers
Classifier: Programming Language :: Python :: 2.6
Classifier: Programming Language :: Python :: 2.7
Classifier: Programming Language :: Python :: 3
Requires-Dist: requests
